ofxstatement_it_banks-0.0.1-py3.6-nspkg.pth
ofxstatement/plugins/webank.py
ofxstatement/plugins/widiba.py
ofxstatement_it_banks-0.0.1.dist-info/LICENSE
ofxstatement_it_banks-0.0.1.dist-info/METADATA
ofxstatement_it_banks-0.0.1.dist-info/WHEEL
ofxstatement_it_banks-0.0.1.dist-info/entry_points.txt
ofxstatement_it_banks-0.0.1.dist-info/namespace_packages.txt
ofxstatement_it_banks-0.0.1.dist-info/top_level.txt
ofxstatement_it_banks-0.0.1.dist-info/zip-safe
ofxstatement_it_banks-0.0.1.dist-info/RECORD
