Metadata-Version: 2.1
Name: ofxstatement-it-banks
Version: 0.0.1
Summary: ofxstatement plugins for some italian banks
Home-page: https://github.com/ecorini/ofxstatement-it-banks
Author: ecorini
Author-email: UNKNOWN
License: GPLv3
Keywords: ofx,banking,statement
Platform: UNKNOWN
Classifier: Development Status :: 3 - Alpha
Classifier: Programming Language :: Python :: 3
Classifier: Natural Language :: English
Classifier: Topic :: Office/Business :: Financial :: Accounting
Classifier: Topic :: Utilities
Classifier: Environment :: Console
Classifier: Operating System :: OS Independent
Classifier: License :: OSI Approved :: GNU General Public License v3 (GPLv3)
Requires-Dist: ofxstatement
Requires-Dist: xlrd
Requires-Dist: datetime
Requires-Dist: pandas
Requires-Dist: lxml
